pylammpsmpi/__init__.py
pylammpsmpi/_version.py
pylammpsmpi/mpi/__init__.py
pylammpsmpi/mpi/lmpmpi.py
pylammpsmpi/wrapper/__init__.py
pylammpsmpi/wrapper/ase.py
pylammpsmpi/wrapper/base.py
pylammpsmpi/wrapper/concurrent.py
pylammpsmpi/wrapper/extended.py
pylammpsmpi-0.3.9.dist-info/METADATA
pylammpsmpi-0.3.9.dist-info/WHEEL
pylammpsmpi-0.3.9.dist-info/licenses/LICENSE
pylammpsmpi-0.3.9.dist-info/RECORD
