Metadata-Version: 2.4
Name: pylammpsmpi
Version: 0.3.9
Summary: Parallel Lammps Python interface - control a mpi4py parallel LAMMPS instance from a serial python process or a Jupyter notebook
Project-URL: Homepage, https://github.com/pyiron/pylammpsmpi
Project-URL: Documentation, https://github.com/pyiron/pylammpsmpi
Project-URL: Repository, https://github.com/pyiron/pylammpsmpi
Author-email: Jan Janssen <janssen@mpie.de>
License: BSD 3-Clause License
License-File: LICENSE
Keywords: pyiron
Classifier: Development Status :: 5 - Production/Stable
Classifier: Intended Audience :: Science/Research
Classifier: License :: OSI Approved :: BSD License
Classifier: Operating System :: OS Independent
Classifier: Programming Language :: Python :: 3.9
Classifier: Programming Language :: Python :: 3.10
Classifier: Programming Language :: Python :: 3.11
Classifier: Programming Language :: Python :: 3.12
Classifier: Programming Language :: Python :: 3.13
Classifier: Topic :: Scientific/Engineering :: Physics
Requires-Python: <3.14,>=3.9
Requires-Dist: executorlib<=1.7.4,>=1.3.0
Requires-Dist: mpi4py<=4.1.1,>=3.1.4
Requires-Dist: numpy<=2.4.1,>=1.23.5
Provides-Extra: ase
Requires-Dist: ase<=3.27.0,>=3.23.0; extra == 'ase'
Requires-Dist: scipy<=1.17.0,>=1.9.3; extra == 'ase'
